odoo/addons/sale_order_import_ubl_requested_delivery/README.rst
odoo/addons/sale_order_import_ubl_requested_delivery/__init__.py
odoo/addons/sale_order_import_ubl_requested_delivery/__manifest__.py
odoo/addons/sale_order_import_ubl_requested_delivery/i18n/it.po
odoo/addons/sale_order_import_ubl_requested_delivery/i18n/sale_order_import_ubl_requested_delivery.pot
odoo/addons/sale_order_import_ubl_requested_delivery/readme/CONTRIBUTORS.md
odoo/addons/sale_order_import_ubl_requested_delivery/readme/DESCRIPTION.md
odoo/addons/sale_order_import_ubl_requested_delivery/static/description/icon.png
odoo/addons/sale_order_import_ubl_requested_delivery/static/description/index.html
odoo/addons/sale_order_import_ubl_requested_delivery/tests/__init__.py
odoo/addons/sale_order_import_ubl_requested_delivery/tests/test_ubl_order_import.py
odoo/addons/sale_order_import_ubl_requested_delivery/tests/samples/UBL-Order-2.0-Example.xml
odoo/addons/sale_order_import_ubl_requested_delivery/tests/samples/UBL-Order-2.1-Example.xml
odoo/addons/sale_order_import_ubl_requested_delivery/tests/samples/UBL-Order-2.2-Example.xml
odoo/addons/sale_order_import_ubl_requested_delivery/wizard/__init__.py
odoo/addons/sale_order_import_ubl_requested_delivery/wizard/sale_order_import.py
odoo_addon_sale_order_import_ubl_requested_delivery-18.0.1.0.0.4.dist-info/METADATA
odoo_addon_sale_order_import_ubl_requested_delivery-18.0.1.0.0.4.dist-info/WHEEL
odoo_addon_sale_order_import_ubl_requested_delivery-18.0.1.0.0.4.dist-info/top_level.txt
odoo_addon_sale_order_import_ubl_requested_delivery-18.0.1.0.0.4.dist-info/RECORD
