Metadata-Version: 2.1
Name: odoo-addon-sale_order_import_ubl_requested_delivery
Version: 18.0.1.0.0.4
Requires-Python: >=3.10
Requires-Dist: odoo-addon-sale_order_import_ubl==18.0.*
Requires-Dist: odoo-addon-sale_order_requested_delivery==18.0.*
Requires-Dist: odoo==18.0.*
Summary: Extract RequestedDeliveryPeriod from sale UBL
Home-page: https://github.com/OCA/edi
License: AGPL-3
Author: Camptocamp, Odoo Community Association (OCA)
Author-email: support@odoo-community.org
Classifier: Programming Language :: Python
Classifier: Framework :: Odoo
Classifier: Framework :: Odoo :: 18.0
Classifier: License :: OSI Approved :: GNU Affero General Public License v3
